Metadata-Version: 2.1
Name: py2js
Version: 1.2.1
Summary: Write javascript in python with python syntax
Home-page: https://github.com/am230/py2js
Author: am230
Author-email: am.230@outlook.jp
License: MIT Licence
Keywords: javascript,convert,translator
Platform: any
Requires: jsbeautifier
Requires: strinpy
License-File: LICENSE
